gicd/__init__.py
gicd/api.py
gicd-4.0.0.dist-info/LICENSE
gicd-4.0.0.dist-info/METADATA
gicd-4.0.0.dist-info/WHEEL
gicd-4.0.0.dist-info/RECORD
