Metadata-Version: 2.1
Name: gicd
Version: 4.0.0
Summary: Python decorator that will automatcially create a GitHub Issue if a decorated function throws an exception
Author: Zeke Marffy
Author-email: zmarffy@me.com
Requires-Python: >=3.8.1,<4.0.0
Classifier: Programming Language :: Python :: 3
Classifier: Programming Language :: Python :: 3.9
Classifier: Programming Language :: Python :: 3.10
Classifier: Programming Language :: Python :: 3.11
